pytest_ty/__init__.py
pytest_ty/plugin.py
pytest_ty-0.1.4.dist-info/licenses/LICENSE
pytest_ty-0.1.4.dist-info/WHEEL
pytest_ty-0.1.4.dist-info/entry_points.txt
pytest_ty-0.1.4.dist-info/METADATA
pytest_ty-0.1.4.dist-info/RECORD
