Metadata-Version: 2.4
Name: pytest-ty
Version: 0.1.4
Summary: A pytest plugin to run the ty type checker
Author: Raphael Boidol
Author-email: Raphael Boidol <pytest-ty@boidol.dev>
License-Expression: MIT
License-File: LICENSE
Classifier: Development Status :: 4 - Beta
Classifier: Framework :: Pytest
Classifier: Intended Audience :: Developers
Classifier: Operating System :: OS Independent
Classifier: Programming Language :: Python
Classifier: Programming Language :: Python :: 3 :: Only
Classifier: Programming Language :: Python :: 3.10
Classifier: Programming Language :: Python :: 3.11
Classifier: Programming Language :: Python :: 3.12
Classifier: Programming Language :: Python :: 3.13
Classifier: Programming Language :: Python :: 3.14
Classifier: Programming Language :: Python :: Implementation :: CPython
Classifier: Programming Language :: Python :: Implementation :: PyPy
Classifier: Topic :: Software Development :: Quality Assurance
Classifier: Topic :: Software Development :: Testing
Requires-Dist: pytest>=7.0.0
Requires-Dist: ty
Requires-Python: >=3.10
Project-URL: Repository, https://github.com/boidolr/pytest-ty
